LICENCE
README.md
setup.py
src/keygener.py
src/keygener.egg-info/PKG-INFO
src/keygener.egg-info/SOURCES.txt
src/keygener.egg-info/dependency_links.txt
src/keygener.egg-info/top_level.txt