Metadata-Version: 2.1
Name: keygener
Version: 1.1
Summary: Password and key generating tool
Home-page: UNKNOWN
Author: Saikrishna T Bijil
License: UNKNOWN
Keywords: key generate,password generate,random number picker
Platform: UNKNOWN
Classifier: Programming Language :: Python :: 3
Classifier: License :: OSI Approved :: MIT License
Classifier: Operating System :: OS Independent
Requires-Python: >=3.6
License-File: LICENCE
